quant_drl/__init__.py
quant_drl/configurations.py
quant_drl/data/__init__.py
quant_drl/data/stock_data.py
quant_drl/environment/__init__.py
quant_drl/environment/portfolio_environment.py
quant_drl/networks/__init__.py
quant_drl/networks/custom_networks.py
quant_drl/tester/__init__.py
quant_drl/tester/tester.py
quant_drl/trainer/__init__.py
quant_drl/trainer/trainer.py
quant_drl/utils/__init__.py
quant_drl/utils/hierarchy_builder.py
quant_drl/utils/logging.py
quant_drl/visualization/__init__.py
quant_drl/visualization/visualization.py
quant_drl_core-0.1.6.dist-info/licenses/LICENSE
quant_drl_core-0.1.6.dist-info/METADATA
quant_drl_core-0.1.6.dist-info/WHEEL
quant_drl_core-0.1.6.dist-info/top_level.txt
quant_drl_core-0.1.6.dist-info/RECORD
