Metadata-Version: 2.4
Name: quant-drl-core
Version: 0.1.6
Summary: Deep Reinforcement Learning for Financial Portfolio Management
Author: Pablo Diego Acosta
Author-email: Pablo Diego Acosta <pablodieaco@gmail.com>
License: MIT License
Project-URL: Homepage, https://github.com/pablodieaco/quant-drl-core
Project-URL: Repository, https://github.com/pablodieaco/quant-drl-core
Project-URL: Issues, https://github.com/pablodieaco/quant-drl-core/issues
Requires-Python: >=3.8
License-File: LICENSE
Requires-Dist: numpy==2.0.0
Requires-Dist: pandas==2.2.3
Requires-Dist: pandas_market_calendars==4.6.1
Requires-Dist: gym==0.23.0
Requires-Dist: matplotlib==3.9.0
Requires-Dist: stable-baselines3[extra]==2.5.0
Requires-Dist: scikit-learn==1.6.1
Requires-Dist: loguru==0.7.3
Requires-Dist: tqdm==4.66.1
Requires-Dist: tensorboard==2.19.0
Requires-Dist: torch==2.6.0
Requires-Dist: plotly==6.0.0
Requires-Dist: seaborn==0.13.2
Requires-Dist: yfinance==0.2.59
Requires-Dist: ta==0.11.0
Requires-Dist: nbformat>=4.2.0
Dynamic: author
Dynamic: license-file
Dynamic: requires-python
